odoo8_addon_l10n_es_aeat_mod111-8.0.2.2.0-nspkg.pth
odoo_addons/l10n_es_aeat_mod111/README.rst
odoo_addons/l10n_es_aeat_mod111/__init__.py
odoo_addons/l10n_es_aeat_mod111/__openerp__.py
odoo_addons/l10n_es_aeat_mod111/data/aeat_export_mod111_data.xml
odoo_addons/l10n_es_aeat_mod111/i18n/bg.po
odoo_addons/l10n_es_aeat_mod111/i18n/ca.po
odoo_addons/l10n_es_aeat_mod111/i18n/ca_ES.po
odoo_addons/l10n_es_aeat_mod111/i18n/cs.po
odoo_addons/l10n_es_aeat_mod111/i18n/en_US.po
odoo_addons/l10n_es_aeat_mod111/i18n/es.po
odoo_addons/l10n_es_aeat_mod111/i18n/es_CO.po
odoo_addons/l10n_es_aeat_mod111/i18n/es_CR.po
odoo_addons/l10n_es_aeat_mod111/i18n/eu.po
odoo_addons/l10n_es_aeat_mod111/i18n/fr.po
odoo_addons/l10n_es_aeat_mod111/i18n/gl.po
odoo_addons/l10n_es_aeat_mod111/i18n/hr.po
odoo_addons/l10n_es_aeat_mod111/i18n/l10n_es_aeat_mod111.pot
odoo_addons/l10n_es_aeat_mod111/i18n/nl.po
odoo_addons/l10n_es_aeat_mod111/i18n/pl.po
odoo_addons/l10n_es_aeat_mod111/i18n/pt.po
odoo_addons/l10n_es_aeat_mod111/i18n/pt_BR.po
odoo_addons/l10n_es_aeat_mod111/i18n/ru.po
odoo_addons/l10n_es_aeat_mod111/i18n/sl.po
odoo_addons/l10n_es_aeat_mod111/i18n/sv.po
odoo_addons/l10n_es_aeat_mod111/i18n/tr.po
odoo_addons/l10n_es_aeat_mod111/i18n/vi.po
odoo_addons/l10n_es_aeat_mod111/models/__init__.py
odoo_addons/l10n_es_aeat_mod111/models/mod111.py
odoo_addons/l10n_es_aeat_mod111/security/ir.model.access.csv
odoo_addons/l10n_es_aeat_mod111/security/ir_rule.xml
odoo_addons/l10n_es_aeat_mod111/static/description/icon.png
odoo_addons/l10n_es_aeat_mod111/static/description/icon_source.svg
odoo_addons/l10n_es_aeat_mod111/views/mod111_view.xml
odoo8_addon_l10n_es_aeat_mod111-8.0.2.2.0.dist-info/METADATA
odoo8_addon_l10n_es_aeat_mod111-8.0.2.2.0.dist-info/WHEEL
odoo8_addon_l10n_es_aeat_mod111-8.0.2.2.0.dist-info/namespace_packages.txt
odoo8_addon_l10n_es_aeat_mod111-8.0.2.2.0.dist-info/top_level.txt
odoo8_addon_l10n_es_aeat_mod111-8.0.2.2.0.dist-info/RECORD
